vivjson/__init__.py
vivjson/__main__.py
vivjson/command_line.py
vivjson/config.py
vivjson/environment.py
vivjson/error.py
vivjson/evaluator.py
vivjson/lexer.py
vivjson/parser.py
vivjson/standard.py
vivjson/statement.py
vivjson/tokens.py
vivjson/viv.py
vivjson-1.0.1.dist-info/licenses/LICENSE
vivjson-1.0.1.dist-info/METADATA
vivjson-1.0.1.dist-info/WHEEL
vivjson-1.0.1.dist-info/entry_points.txt
vivjson-1.0.1.dist-info/top_level.txt
vivjson-1.0.1.dist-info/RECORD
