Metadata-Version: 2.4
Name: vivjson
Version: 1.0.1
Summary: VivJson that is the embedded scripting language and the extension of JSON.
Author-email: Fumiaki Motegi <motegi@benesult.com>
License-Expression: Apache-2.0
Project-URL: Homepage, https://github.com/benesult/vivjson-python
Project-URL: Source, https://github.com/benesult/vivjson-python
Project-URL: Repository, https://github.com/benesult/vivjson-python.git
Project-URL: Issues, https://github.com/benesult/vivjson-python/issues
Keywords: script,embed,embedded,language,JSON,development
Classifier: Development Status :: 5 - Production/Stable
Classifier: Intended Audience :: Developers
Classifier: Topic :: File Formats :: JSON
Classifier: Topic :: Software Development :: Interpreters
Classifier: Programming Language :: Python :: 3
Classifier: Programming Language :: Python :: 3.9
Classifier: Programming Language :: Python :: 3.10
Classifier: Programming Language :: Python :: 3.11
Classifier: Programming Language :: Python :: 3.12
Classifier: Programming Language :: Python :: 3.13
Classifier: Programming Language :: Python :: 3.14
Classifier: Programming Language :: Python :: 3 :: Only
Requires-Python: >=3.9
License-File: LICENSE
Provides-Extra: dev
Provides-Extra: test
Requires-Dist: pytest-cov~=6.0.0; extra == "test"
Dynamic: license-file
